openai_tool_generator/__init__.py
openai_tool_generator/generate_tool_definition.py
openai_tool_generator-0.2.0.dist-info/LICENSE
openai_tool_generator-0.2.0.dist-info/METADATA
openai_tool_generator-0.2.0.dist-info/WHEEL
openai_tool_generator-0.2.0.dist-info/entry_points.txt
openai_tool_generator-0.2.0.dist-info/top_level.txt
openai_tool_generator-0.2.0.dist-info/RECORD
