Metadata-Version: 2.1
Name: openai_tool_generator
Version: 0.2.0
Summary: Generate OpenAI Compatible tool definitions by parsing Python functions
Home-page: https://github.com/ronniebasak/openai-function-generator
Author: Sohan Basak
Author-email: ronnie.basak96@gmail.com
Classifier: Programming Language :: Python :: 3
Classifier: License :: OSI Approved :: MIT License
Classifier: Operating System :: OS Independent
Requires-Python: >=3.6
License-File: LICENSE
